README.md
setup.py
JetKit_Flask.egg-info/PKG-INFO
JetKit_Flask.egg-info/SOURCES.txt
JetKit_Flask.egg-info/dependency_links.txt
JetKit_Flask.egg-info/not-zip-safe
JetKit_Flask.egg-info/requires.txt
JetKit_Flask.egg-info/top_level.txt
jetkit/__init__.py
jetkit/api/__init__.py
jetkit/api/asset/__init__.py
jetkit/api/asset/schema.py
jetkit/api/auth/__init__.py
jetkit/api/user/__init__.py
jetkit/api/user/schema.py
jetkit/aws/__init__.py
jetkit/aws/s3.py
jetkit/db/__init__.py
jetkit/db/bases.py
jetkit/db/extid.py
jetkit/db/owned.py
jetkit/db/soft_deletable.py
jetkit/db/upsert.py
jetkit/db/utils.py
jetkit/db/model/__init__.py
jetkit/db/query/__init__.py
jetkit/db/query/filter.py
jetkit/db/query/soft_deletable.py
jetkit/mail/__init__.py
jetkit/mail/base.py
jetkit/mail/constant.py
jetkit/mail/impl/__init__.py
jetkit/mail/impl/dummy/__init__.py
jetkit/mail/impl/mailgun/__init__.py
jetkit/model/__init__.py
jetkit/model/asset.py
jetkit/model/user.py