Metadata-Version: 2.1
Name: JetKit-Flask
Version: 8.1.0
Summary: Rapid web application development.
Home-page: https://github.com/jetbridge/jetkit-flask
Author: JetBridge
Author-email: mischa@jetbridge.com
License: MIT
Platform: any
Requires-Python: >=3.6.0
